[
  {
    "destination": "Ouagadougou, Burkina Faso",
    "experience": "Discover the heart of West Africa! Explore vibrant markets, local music festivals, and cultural heritage sites.",
    "region": "West Africa",
    "booking_link": "https://calendly.com/hennymoneyafric/ouagadougou-tour"
  },
  {
    "destination": "Lagos, Nigeria",
    "experience": "Experience Africa’s music capital! Enjoy city tours, Afrobeat nights, and cultural adventures.",
    "region": "West Africa",
    "booking_link": "https://calendly.com/hennymoneyafric/lagos-tour"
  },
  {
    "destination": "Accra, Ghana",
    "experience": "Explore the coastal beauty, local rhythms, and rich history of Ghana.",
    "region": "West Africa",
    "booking_link": "https://calendly.com/hennymoneyafric/accra-tour"
  }
]
